{
  "header": "X:1\nT:Věřím Ti, Pane můj\nM:4/4\nL:1/4\nQ:1/4=120\nK:F",
  "blocks": [
    {
      "type": "verse",
      "body": "\"^Verse\"\nz/2 F/2 F/2 F/2 G A | _B/2 A/2 G F z |\nw: Zpí- vej- me pí- seň na- * dě- je\nz/2 A/2 A/2 A/2 _B c | c _B/2 A/2 G z |\nw: bra- trům a se- strám pla- čí- * cím.\nz/2 G/2 A/2 _B/2 A G | A G F z |\nw: Ať se vám srd- ce ne- chvě- je!\nF F/2 F/2 d c | _B/2 A/2 G F2 |\nw: Tě- ší nás Je- žíš, Bo- * ží Syn.",
      "notes": [
        {
          "pitch": null,
          "durationBeats": 0.5,
          "lyric": null,
          "syllabic": null,
          "chord": null
        },
        {
          "pitch": 65,
          "durationBeats": 0.5,
          "lyric": "Zpí",
          "syllabic": "begin",
          "chord": null
        },
        {
          "pitch": 65,
          "durationBeats": 0.5,
          "lyric": "vej",
          "syllabic": "middle",
          "chord": null
        },
        {
          "pitch": 65,
          "durationBeats": 0.5,
          "lyric": "me",
          "syllabic": "end",
          "chord": null
        },
        {
          "pitch": 67,
          "durationBeats": 1.0,
          "lyric": "pí",
          "syllabic": "begin",
          "chord": null
        },
        {
          "pitch": 69,
          "durationBeats": 1.0,
          "lyric": "seň",
          "syllabic": "end",
          "chord": null
        },
        {
          "pitch": 70,
          "durationBeats": 0.5,
          "lyric": "na",
          "syllabic": "begin",
          "chord": null
        },
        {
          "pitch": 69,
          "durationBeats": 0.5,
          "lyric": null,
          "syllabic": null,
          "chord": null
        },
        {
          "pitch": 67,
          "durationBeats": 1.0,
          "lyric": "dě",
          "syllabic": "middle",
          "chord": null
        },
        {
          "pitch": 65,
          "durationBeats": 1.0,
          "lyric": "je",
          "syllabic": "end",
          "chord": null
        },
        {
          "pitch": null,
          "durationBeats": 1.0,
          "lyric": null,
          "syllabic": null,
          "chord": null
        },
        {
          "pitch": null,
          "durationBeats": 0.5,
          "lyric": null,
          "syllabic": null,
          "chord": null
        },
        {
          "pitch": 69,
          "durationBeats": 0.5,
          "lyric": "bra",
          "syllabic": "begin",
          "chord": null
        },
        {
          "pitch": 69,
          "durationBeats": 0.5,
          "lyric": "trům",
          "syllabic": "end",
          "chord": null
        },
        {
          "pitch": 69,
          "durationBeats": 0.5,
          "lyric": "a",
          "syllabic": "single",
          "chord": null
        },
        {
          "pitch": 70,
          "durationBeats": 1.0,
          "lyric": "se",
          "syllabic": "begin",
          "chord": null
        },
        {
          "pitch": 72,
          "durationBeats": 1.0,
          "lyric": "strám",
          "syllabic": "end",
          "chord": null
        },
        {
          "pitch": 72,
          "durationBeats": 1.0,
          "lyric": "pla",
          "syllabic": "begin",
          "chord": null
        },
        {
          "pitch": 70,
          "durationBeats": 0.5,
          "lyric": "čí",
          "syllabic": "middle",
          "chord": null
        },
        {
          "pitch": 69,
          "durationBeats": 0.5,
          "lyric": null,
          "syllabic": null,
          "chord": null
        },
        {
          "pitch": 67,
          "durationBeats": 1.0,
          "lyric": "cím.",
          "syllabic": "end",
          "chord": null
        },
        {
          "pitch": null,
          "durationBeats": 1.0,
          "lyric": null,
          "syllabic": null,
          "chord": null
        },
        {
          "pitch": null,
          "durationBeats": 0.5,
          "lyric": null,
          "syllabic": null,
          "chord": null
        },
        {
          "pitch": 67,
          "durationBeats": 0.5,
          "lyric": "Ať",
          "syllabic": "single",
          "chord": null
        },
        {
          "pitch": 69,
          "durationBeats": 0.5,
          "lyric": "se",
          "syllabic": "single",
          "chord": null
        },
        {
          "pitch": 70,
          "durationBeats": 0.5,
          "lyric": "vám",
          "syllabic": "single",
          "chord": null
        },
        {
          "pitch": 69,
          "durationBeats": 1.0,
          "lyric": "srd",
          "syllabic": "begin",
          "chord": null
        },
        {
          "pitch": 67,
          "durationBeats": 1.0,
          "lyric": "ce",
          "syllabic": "end",
          "chord": null
        },
        {
          "pitch": 69,
          "durationBeats": 1.0,
          "lyric": "ne",
          "syllabic": "begin",
          "chord": null
        },
        {
          "pitch": 67,
          "durationBeats": 1.0,
          "lyric": "chvě",
          "syllabic": "middle",
          "chord": null
        },
        {
          "pitch": 65,
          "durationBeats": 1.0,
          "lyric": "je!",
          "syllabic": "end",
          "chord": null
        },
        {
          "pitch": null,
          "durationBeats": 1.0,
          "lyric": null,
          "syllabic": null,
          "chord": null
        },
        {
          "pitch": 65,
          "durationBeats": 1.0,
          "lyric": "Tě",
          "syllabic": "begin",
          "chord": null
        },
        {
          "pitch": 65,
          "durationBeats": 0.5,
          "lyric": "ší",
          "syllabic": "end",
          "chord": null
        },
        {
          "pitch": 65,
          "durationBeats": 0.5,
          "lyric": "nás",
          "syllabic": "single",
          "chord": null
        },
        {
          "pitch": 74,
          "durationBeats": 1.0,
          "lyric": "Je",
          "syllabic": "begin",
          "chord": null
        },
        {
          "pitch": 72,
          "durationBeats": 1.0,
          "lyric": "žíš,",
          "syllabic": "end",
          "chord": null
        },
        {
          "pitch": 70,
          "durationBeats": 0.5,
          "lyric": "Bo",
          "syllabic": "begin",
          "chord": null
        },
        {
          "pitch": 69,
          "durationBeats": 0.5,
          "lyric": null,
          "syllabic": null,
          "chord": null
        },
        {
          "pitch": 67,
          "durationBeats": 1.0,
          "lyric": "ží",
          "syllabic": "end",
          "chord": null
        },
        {
          "pitch": 65,
          "durationBeats": 2.0,
          "lyric": "Syn.",
          "syllabic": "single",
          "chord": null
        }
      ]
    }
  ]
}
