{
  "header": "X:1\nT:Rájem\nM:4/4\nL:1/4\nQ:1/4=120\nK:E",
  "blocks": [
    {
      "type": "verse",
      "body": "\"^Verse\"\nB4 | ^G/2 ^G ^G/2 z2 |\nw: Znám ti- síc jmen,\n^F/2 ^F/2 ^F ^G z/2 ^G/2 | B/2 B z/2 ^c B/2 |\nw: je- di- ný z~nich je sva- tý. Ó! *",
      "notes": [
        {
          "pitch": 71,
          "durationBeats": 4.0,
          "lyric": "Znám",
          "syllabic": "single",
          "chord": null
        },
        {
          "pitch": 68,
          "durationBeats": 0.5,
          "lyric": "ti",
          "syllabic": "begin",
          "chord": null
        },
        {
          "pitch": 68,
          "durationBeats": 1.0,
          "lyric": "síc",
          "syllabic": "end",
          "chord": null
        },
        {
          "pitch": 68,
          "durationBeats": 0.5,
          "lyric": "jmen,",
          "syllabic": "single",
          "chord": null
        },
        {
          "pitch": null,
          "durationBeats": 2.0,
          "lyric": null,
          "syllabic": null,
          "chord": null
        },
        {
          "pitch": 66,
          "durationBeats": 0.5,
          "lyric": "je",
          "syllabic": "begin",
          "chord": null
        },
        {
          "pitch": 66,
          "durationBeats": 0.5,
          "lyric": "di",
          "syllabic": "middle",
          "chord": null
        },
        {
          "pitch": 66,
          "durationBeats": 1.0,
          "lyric": "ný",
          "syllabic": "end",
          "chord": null
        },
        {
          "pitch": 68,
          "durationBeats": 1.0,
          "lyric": "z nich",
          "syllabic": "single",
          "chord": null
        },
        {
          "pitch": null,
          "durationBeats": 0.5,
          "lyric": null,
          "syllabic": null,
          "chord": null
        },
        {
          "pitch": 68,
          "durationBeats": 0.5,
          "lyric": "je",
          "syllabic": "single",
          "chord": null
        },
        {
          "pitch": 71,
          "durationBeats": 0.5,
          "lyric": "sva",
          "syllabic": "begin",
          "chord": null
        },
        {
          "pitch": 71,
          "durationBeats": 1.5,
          "lyric": "tý.",
          "syllabic": "end",
          "chord": null
        },
        {
          "pitch": null,
          "durationBeats": 0.5,
          "lyric": null,
          "syllabic": null,
          "chord": null
        },
        {
          "pitch": 73,
          "durationBeats": 1.0,
          "lyric": "Ó!",
          "syllabic": "single",
          "chord": null
        },
        {
          "pitch": 71,
          "durationBeats": 0.5,
          "lyric": null,
          "syllabic": null,
          "chord": null
        }
      ]
    },
    {
      "type": "chorus",
      "body": "\"^Chorus\"\n|: E/2 E/2 E/2 E/4 ^c/2 B |\nw: Čas tvůj k~nám se vrá- tí,\n^c/2 | ^G ^G/2 ^G/4 ^F/2 E/2 ^C/4 B,/2 |\nw: já znám, znám to jmé- no sva- tý,\nE/2 E/2 E/2 E/4 ^c/2 B |\nw: čas tvůj k~nám se vrá- tí,\n^c/2 | ^G ^F E2 :|\nw: jdu s~jmé- nem tvým.",
      "notes": [
        {
          "pitch": 64,
          "durationBeats": 0.5,
          "lyric": "Čas",
          "syllabic": "single",
          "chord": null
        },
        {
          "pitch": 64,
          "durationBeats": 0.5,
          "lyric": "tvůj",
          "syllabic": "single",
          "chord": null
        },
        {
          "pitch": 64,
          "durationBeats": 0.75,
          "lyric": "k nám",
          "syllabic": "single",
          "chord": null
        },
        {
          "pitch": 64,
          "durationBeats": 0.25,
          "lyric": "se",
          "syllabic": "single",
          "chord": null
        },
        {
          "pitch": 73,
          "durationBeats": 0.5,
          "lyric": "vrá",
          "syllabic": "begin",
          "chord": null
        },
        {
          "pitch": 71,
          "durationBeats": 1.0,
          "lyric": "tí,",
          "syllabic": "end",
          "chord": null
        },
        {
          "pitch": 73,
          "durationBeats": 0.5,
          "lyric": "já",
          "syllabic": "single",
          "chord": null
        },
        {
          "pitch": 68,
          "durationBeats": 1.0,
          "lyric": "znám,",
          "syllabic": "single",
          "chord": null
        },
        {
          "pitch": 68,
          "durationBeats": 0.75,
          "lyric": "znám",
          "syllabic": "single",
          "chord": null
        },
        {
          "pitch": 68,
          "durationBeats": 0.25,
          "lyric": "to",
          "syllabic": "single",
          "chord": null
        },
        {
          "pitch": 66,
          "durationBeats": 0.5,
          "lyric": "jmé",
          "syllabic": "begin",
          "chord": null
        },
        {
          "pitch": 64,
          "durationBeats": 0.5,
          "lyric": "no",
          "syllabic": "end",
          "chord": null
        },
        {
          "pitch": 61,
          "durationBeats": 0.25,
          "lyric": "sva",
          "syllabic": "begin",
          "chord": null
        },
        {
          "pitch": 59,
          "durationBeats": 0.75,
          "lyric": "tý,",
          "syllabic": "end",
          "chord": null
        },
        {
          "pitch": 64,
          "durationBeats": 0.5,
          "lyric": "čas",
          "syllabic": "single",
          "chord": null
        },
        {
          "pitch": 64,
          "durationBeats": 0.5,
          "lyric": "tvůj",
          "syllabic": "single",
          "chord": null
        },
        {
          "pitch": 64,
          "durationBeats": 0.75,
          "lyric": "k nám",
          "syllabic": "single",
          "chord": null
        },
        {
          "pitch": 64,
          "durationBeats": 0.25,
          "lyric": "se",
          "syllabic": "single",
          "chord": null
        },
        {
          "pitch": 73,
          "durationBeats": 0.5,
          "lyric": "vrá",
          "syllabic": "begin",
          "chord": null
        },
        {
          "pitch": 71,
          "durationBeats": 1.0,
          "lyric": "tí,",
          "syllabic": "end",
          "chord": null
        },
        {
          "pitch": 73,
          "durationBeats": 0.5,
          "lyric": "jdu",
          "syllabic": "single",
          "chord": null
        },
        {
          "pitch": 68,
          "durationBeats": 1.0,
          "lyric": "s jmé",
          "syllabic": "begin",
          "chord": null
        },
        {
          "pitch": 66,
          "durationBeats": 1.0,
          "lyric": "nem",
          "syllabic": "end",
          "chord": null
        },
        {
          "pitch": 64,
          "durationBeats": 2.0,
          "lyric": "tvým.",
          "syllabic": "single",
          "chord": null
        }
      ]
    },
    {
      "type": "chorus",
      "body": "\"^Chorus 2\"\nB,/4 B,/2 B,/4 ^D/2 B,/2 ^D/2 E |\nw: Kde vlád- nou jmé- na li- dí,\n^G/2 | E E/2 ^G/4 ^F/2 E/2 ^C/4 B,/2 |\nw: tam znám, znám to jmé- no sva- tý,\nB,/4 B,/2 B,/4 ^D/2 B,/2 ^D/2 E |\nw: kde vů- lí zlou se ří- dí,\nE/2 | ^G ^F E2 |\nw: jdu s~jmé- nem tvým.",
      "notes": [
        {
          "pitch": 59,
          "durationBeats": 0.25,
          "lyric": "Kde",
          "syllabic": "single",
          "chord": null
        },
        {
          "pitch": 59,
          "durationBeats": 0.5,
          "lyric": "vlád",
          "syllabic": "begin",
          "chord": null
        },
        {
          "pitch": 59,
          "durationBeats": 0.25,
          "lyric": "nou",
          "syllabic": "end",
          "chord": null
        },
        {
          "pitch": 63,
          "durationBeats": 0.5,
          "lyric": "jmé",
          "syllabic": "begin",
          "chord": null
        },
        {
          "pitch": 59,
          "durationBeats": 0.5,
          "lyric": "na",
          "syllabic": "end",
          "chord": null
        },
        {
          "pitch": 63,
          "durationBeats": 0.5,
          "lyric": "li",
          "syllabic": "begin",
          "chord": null
        },
        {
          "pitch": 64,
          "durationBeats": 1.0,
          "lyric": "dí,",
          "syllabic": "end",
          "chord": null
        },
        {
          "pitch": 68,
          "durationBeats": 0.5,
          "lyric": "tam",
          "syllabic": "single",
          "chord": null
        },
        {
          "pitch": 64,
          "durationBeats": 1.0,
          "lyric": "znám,",
          "syllabic": "single",
          "chord": null
        },
        {
          "pitch": 64,
          "durationBeats": 0.75,
          "lyric": "znám",
          "syllabic": "single",
          "chord": null
        },
        {
          "pitch": 68,
          "durationBeats": 0.25,
          "lyric": "to",
          "syllabic": "single",
          "chord": null
        },
        {
          "pitch": 66,
          "durationBeats": 0.5,
          "lyric": "jmé",
          "syllabic": "begin",
          "chord": null
        },
        {
          "pitch": 64,
          "durationBeats": 0.5,
          "lyric": "no",
          "syllabic": "end",
          "chord": null
        },
        {
          "pitch": 61,
          "durationBeats": 0.25,
          "lyric": "sva",
          "syllabic": "begin",
          "chord": null
        },
        {
          "pitch": 59,
          "durationBeats": 0.75,
          "lyric": "tý,",
          "syllabic": "end",
          "chord": null
        },
        {
          "pitch": 59,
          "durationBeats": 0.25,
          "lyric": "kde",
          "syllabic": "single",
          "chord": null
        },
        {
          "pitch": 59,
          "durationBeats": 0.5,
          "lyric": "vů",
          "syllabic": "begin",
          "chord": null
        },
        {
          "pitch": 59,
          "durationBeats": 0.25,
          "lyric": "lí",
          "syllabic": "end",
          "chord": null
        },
        {
          "pitch": 63,
          "durationBeats": 0.5,
          "lyric": "zlou",
          "syllabic": "single",
          "chord": null
        },
        {
          "pitch": 59,
          "durationBeats": 0.5,
          "lyric": "se",
          "syllabic": "single",
          "chord": null
        },
        {
          "pitch": 63,
          "durationBeats": 0.5,
          "lyric": "ří",
          "syllabic": "begin",
          "chord": null
        },
        {
          "pitch": 64,
          "durationBeats": 1.0,
          "lyric": "dí,",
          "syllabic": "end",
          "chord": null
        },
        {
          "pitch": 64,
          "durationBeats": 0.5,
          "lyric": "jdu",
          "syllabic": "single",
          "chord": null
        },
        {
          "pitch": 68,
          "durationBeats": 1.0,
          "lyric": "s jmé",
          "syllabic": "begin",
          "chord": null
        },
        {
          "pitch": 66,
          "durationBeats": 1.0,
          "lyric": "nem",
          "syllabic": "end",
          "chord": null
        },
        {
          "pitch": 64,
          "durationBeats": 2.0,
          "lyric": "tvým.",
          "syllabic": "single",
          "chord": null
        }
      ]
    }
  ]
}
